{"UCqcbQf6yw5KzRoDDcZ_wBSw": ["0d727qv_MYs", "1Mw6-oyOFjM", "PshNZ1zztgo", "EWAUutf9xKQ", "EnjrRDwycK0"], "UCqzK60-oUOEq36uU9B1MMUg": ["f7QLiOaQqYI", "ma_MMwLaFV8", "5BfcR6erPyo", "EjKjl8NVMGo", "_zKymc5zmU8"], "UCawZsQWqfGSbCI5yjkdVkTA": ["64T7EXN1j_A", "Q1tgc3WTb2k", "EX_gPbb_M7E", "NosPd9LxMDs", "hci2xuWeEQ8"], "UCttqpACIkQqh83L2cHrY9Gg": ["bEQ8sSNzXjQ", "209mYT7IvHI", "A0M0RRwj-V4", "lJKkuuAo4Qo", "AgufCHC6WU4"], "UCR9j1jqqB5Rse69wjUnbYwA": ["JYa2UcO_iUs", "VRNEr8_cTj8", "HcfFUGEuO6s", "nx3z07H8Va8", "7SrkvlgIKFs"], "UCNJ1Ymd5yFuUPtn21xtRbbw": ["TK3r4XbhtMY", "Dl3Olh29_nY", "8eqdMpCz9tc", "chr2I7CZTfk", "9hv4nr_46Ao"], "UChpleBmo18P08aKCIgti38g": ["p7SRuKWZMvQ", "lwrPjDQkVCQ", "aAXLmaQFn_E", "8uGqOAYmPfw", "f186idimlA8"], "UCbY9xX3_jW5c2fjlZVBI4cg": ["Ss1zBzFnISk", "GzygJtYmtCY", "QKddqaqOw8o", "zphET-QsAJk", "vHoyHfzhfBY"], "UCpdyFxSktWo3W6kMYfmk6lg": ["8x7La1X2Zhc", "N2c5qnxYxfE", "7zC8oD5dps4", "RjeaL6876r8", "CxUrFYHSlSA"], "UCIgnGlGkVRhd4qNFcEwLL4A": ["6EQP8-D37bs", "WTdooXYkltc", "7prw229V_vM", "iNM5z8cCH8w", "2IFMIkN2HaU"], "UCWZwfV3ICOt3uEPpW6hYK4g": ["fQ1QMtjAexA", "7o_mCOqxFOM", "rBMtz5YEGAk", "Qf_9mUrmMi8", "1FrJrOdYtSs"]}