{"UCqcbQf6yw5KzRoDDcZ_wBSw": ["mA8C55NLYzw", "tUkD0oj92Qg", "C6IHcZbCMAM", "wX_EVS3UOwU", "Mz7W0qNlmOw"], "UCqzK60-oUOEq36uU9B1MMUg": ["f7QLiOaQqYI", "ma_MMwLaFV8", "5BfcR6erPyo", "EjKjl8NVMGo", "_zKymc5zmU8"], "UCawZsQWqfGSbCI5yjkdVkTA": ["LnsPK0ZOPkg", "YiFC3Z_bCDU", "5dfu6NvnTZM", "Cqfh7QBbQw4", "I0me2uEbfuE"], "UCttqpACIkQqh83L2cHrY9Gg": ["QxGTox4Wv3U", "EP__YYXxIP4", "ZxM5ojFDdys", "Xz0lhtiLxlo", "gEeDAyAAtzo"], "UCR9j1jqqB5Rse69wjUnbYwA": ["8RM-u7TkYpw", "rodYMnGntdI", "kKucCudlHZs", "8PVPMc6XCko", "pEQvElSxKOk"], "UCNJ1Ymd5yFuUPtn21xtRbbw": ["Iar4yweKGoI", "1PxEziv5XIU", "2_DPnzoiHaY", "Cru804JMjPI", "zizoDORjmlQ"], "UChpleBmo18P08aKCIgti38g": ["retqU5rjzzI", "syx_8UlEWlA", "3B1c6Kq_aY0", "Yd10X5VyMng", "W4iSvbg4f68"], "UCbY9xX3_jW5c2fjlZVBI4cg": ["2JOKwaVZEBc", "mAPMzgLymOQ", "XGDZbxAOEtc", "DHH9MqJe0YM", "tYasEbsZfug"], "UCpdyFxSktWo3W6kMYfmk6lg": ["yokNPWuKjUM", "ngftMkZOxZQ", "ssxJJUubGuo", "qTRvm7ePvYc", "1OsNUhTpzJY"], "UCIgnGlGkVRhd4qNFcEwLL4A": ["YRyjkmmW5Ek", "KRE8JqTAEQk", "KaQbt6NYrzY", "ZqRtR6Z2U6U", "qWzo3ws0uWU"], "UCWZwfV3ICOt3uEPpW6hYK4g": ["qIABC8ERuiY", "t6NxHM5peus", "rRrBbyv3ChM", "xEoVCx9CmxQ", "YkpEX_jlb04"]}