{"UCqcbQf6yw5KzRoDDcZ_wBSw": ["CB43-oFnavw", "uz6cI0RpllM", "2WM3CQhc1bY", "64cdhWFvxeY", "HctuXVQci4E"], "UCqzK60-oUOEq36uU9B1MMUg": ["-ieN2RueDlU", "N7jX2CqZ6CE", "vXnlc-T0tfg", "HEkjTYr8Mkc", "d0uFDa57D1k"], "UCawZsQWqfGSbCI5yjkdVkTA": ["fkVfG-dtURY", "dIKvlXSr-qk", "ZwW0RLdPVsU", "ngj7ppxBQaU", "3tu1-csf6OU"], "UCttqpACIkQqh83L2cHrY9Gg": ["KiC3OICLgic", "T-44sKtweH8", "oXFPiFcPEOE", "fV9kPSvYK54", "NEs_zZ8WgeA"], "UCR9j1jqqB5Rse69wjUnbYwA": ["BqVIYcU29ss", "vbx8T1vErtc", "p6peD0Sv63Y", "TC94ECQhI1U", "Opsz0vsyJhQ"], "UCNJ1Ymd5yFuUPtn21xtRbbw": ["Xn_5aIhrJOE", "jWsd2fRzpUo", "wPBD6wTap7g", "eczw9k3r6Ic", "dbgL00a7_xs"], "UChpleBmo18P08aKCIgti38g": ["BeTAVG5E07s", "3VMlvFUURs8", "eg0nUoZ3Ujk", "803N2AHUejo", "SpZ641bJGxU"], "UCbY9xX3_jW5c2fjlZVBI4cg": ["XK8Kp4Tkb88", "7tCyEMvPQ1E", "P1S3wDeP-Co", "_IkeAkx_zeQ", "H7xvG_MYuTI"], "UCpdyFxSktWo3W6kMYfmk6lg": ["3NljwAWS-sE", "i6pSkptrZz0", "vQ6qNqKEk5E", "WpxobhvRXLA", "IpEivcuaFIc"], "UCIgnGlGkVRhd4qNFcEwLL4A": ["qoSXF6FjqT4", "enOlq9bEtUM", "4LOGKADgTew", "JDIqb-WqO3U", "2SqORhe7pqM"], "UCWZwfV3ICOt3uEPpW6hYK4g": ["PVs7ZnWXTcc", "jGSt9OLHj5U", "ZhKJnVhWcbQ", "geR9PeCuHK4", "0c_NpEBLltM"]}